textures/__init__.py
textures/clean_text.py
textures/extract.py
textures/features.py
textures/find.py
textures-0.1.6.dist-info/LICENSE
textures-0.1.6.dist-info/METADATA
textures-0.1.6.dist-info/WHEEL
textures-0.1.6.dist-info/top_level.txt
textures-0.1.6.dist-info/RECORD
