Metadata-Version: 2.1
Name: textures
Version: 0.1.6
Summary: A python package to extract features from text data
Home-page: https://github.com/mcnakhaee/textures
Author: Muhammad Chenariyan Nakhaee
Author-email: UNKNOWN
License: UNKNOWN
Platform: UNKNOWN
Requires-Dist: pandas
Requires-Dist: spacy
Requires-Dist: pyenchant
Requires-Dist: textblob
Requires-Dist: nltk
Requires-Dist: langdetect
Requires-Dist: textstat
Requires-Dist: pytest
